{
  "uid": "1440f0671a85a23be73cba7aba7157807f5c4c6f.boutiques",
  "package": {
    "name": "afni",
    "version": "24.2.06",
    "docker": "afni/afni_make_build:AFNI_24.2.06",
    "docs": {
      "title": "AFNI",
      "description": "AFNI (Analysis of Functional NeuroImages) is a leading software suite of C, Python, R programs and shell scripts primarily developed for the analysis and display of multiple MRI modalities: anatomical, functional MRI (FMRI) and diffusion weighted (DW) data. It is freely available (both as open source code and as precompiled binaries) for research purposes. The software is made to run on virtually any Unix system with X11 and Motif displays. Binary packages are provided for MacOS and Linux systems such as Fedora, CentOS/Red Hat and Ubuntu (which includes the Windows Subsystem for Linux).",
      "authors": [],
      "literature": [],
      "urls": [
        "https://afni.nimh.nih.gov/"
      ]
    }
  },
  "command": {
    "base": {
      "id": 9,
      "name": "SurfDist",
      "outputs": [
        {
          "id": 8,
          "name": "distances",
          "tokens": [
            "example.1D"
          ],
          "docs": {
            "title": "Distances file",
            "description": "File containing the distances between nodes",
            "authors": [],
            "literature": [],
            "urls": []
          }
        }
      ],
      "docs": {
        "title": null,
        "description": "Calculate shortest distance between node pairs on a surface mesh.",
        "authors": [
          "AFNI Developers"
        ],
        "literature": [],
        "urls": [
          "https://afni.nimh.nih.gov/"
        ]
      }
    },
    "body": {
      "type": "struct",
      "name": "SurfDist",
      "groups": [
        {
          "cargs": [
            {
              "tokens": [
                "SurfDist"
              ],
              "join": null
            }
          ],
          "join": null
        },
        {
          "cargs": [
            {
              "tokens": [
                {
                  "base": {
                    "id": 0,
                    "name": "surface",
                    "outputs": [],
                    "docs": {
                      "title": "Surface",
                      "description": "Surface on which distances are computed.",
                      "authors": [],
                      "literature": [],
                      "urls": []
                    }
                  },
                  "body": {
                    "type": "file",
                    "resolveParent": false,
                    "mutable": false
                  },
                  "list": null,
                  "nullable": false,
                  "choices": null,
                  "defaultValue": null
                }
              ],
              "join": null
            }
          ],
          "join": null
        },
        {
          "cargs": [
            {
              "tokens": [
                {
                  "base": {
                    "id": 1,
                    "name": "nodepairs",
                    "outputs": [],
                    "docs": {
                      "title": "Node pairs",
                      "description": "Specify node pairs for distance computation.",
                      "authors": [],
                      "literature": [],
                      "urls": []
                    }
                  },
                  "body": {
                    "type": "file",
                    "resolveParent": false,
                    "mutable": false
                  },
                  "list": null,
                  "nullable": false,
                  "choices": null,
                  "defaultValue": null
                }
              ],
              "join": null
            }
          ],
          "join": null
        },
        {
          "cargs": [
            {
              "tokens": [
                "-node_path_do"
              ],
              "join": null
            },
            {
              "tokens": [
                {
                  "base": {
                    "id": 2,
                    "name": "node_path_do",
                    "outputs": [],
                    "docs": {
                      "title": "Node path display object",
                      "description": "Output the shortest path between each node pair as a SUMA Displayable object.",
                      "authors": [],
                      "literature": [],
                      "urls": []
                    }
                  },
                  "body": {
                    "type": "string"
                  },
                  "list": null,
                  "nullable": true,
                  "choices": null,
                  "defaultValue": {
                    "_special": "SET_TO_NONE"
                  }
                }
              ],
              "join": null
            }
          ],
          "join": null
        },
        {
          "cargs": [
            {
              "tokens": [
                {
                  "base": {
                    "id": 3,
                    "name": "euclidean",
                    "outputs": [],
                    "docs": {
                      "title": "Euclidean distance flag",
                      "description": "Calculate Euclidean distance, rather than graph distance.",
                      "authors": [],
                      "literature": [],
                      "urls": []
                    }
                  },
                  "body": {
                    "type": "bool",
                    "valueTrue": [
                      "-Euclidean"
                    ],
                    "valueFalse": []
                  },
                  "list": null,
                  "nullable": false,
                  "choices": null,
                  "defaultValue": false
                }
              ],
              "join": null
            }
          ],
          "join": null
        },
        {
          "cargs": [
            {
              "tokens": [
                {
                  "base": {
                    "id": 4,
                    "name": "euclidian",
                    "outputs": [],
                    "docs": {
                      "title": "Euclidian distance flag",
                      "description": "Synonym for '-Euclidean'.",
                      "authors": [],
                      "literature": [],
                      "urls": []
                    }
                  },
                  "body": {
                    "type": "bool",
                    "valueTrue": [
                      "-Euclidian"
                    ],
                    "valueFalse": []
                  },
                  "list": null,
                  "nullable": false,
                  "choices": null,
                  "defaultValue": false
                }
              ],
              "join": null
            }
          ],
          "join": null
        },
        {
          "cargs": [
            {
              "tokens": [
                {
                  "base": {
                    "id": 5,
                    "name": "graph",
                    "outputs": [],
                    "docs": {
                      "title": "Graph distance flag",
                      "description": "Calculate distance along the mesh (default).",
                      "authors": [],
                      "literature": [],
                      "urls": []
                    }
                  },
                  "body": {
                    "type": "bool",
                    "valueTrue": [
                      "-graph"
                    ],
                    "valueFalse": []
                  },
                  "list": null,
                  "nullable": false,
                  "choices": null,
                  "defaultValue": false
                }
              ],
              "join": null
            }
          ],
          "join": null
        },
        {
          "cargs": [
            {
              "tokens": [
                "-from_node"
              ],
              "join": null
            },
            {
              "tokens": [
                {
                  "base": {
                    "id": 6,
                    "name": "from_node",
                    "outputs": [],
                    "docs": {
                      "title": "From node",
                      "description": "Specify one starting node for pair calculation.",
                      "authors": [],
                      "literature": [],
                      "urls": []
                    }
                  },
                  "body": {
                    "type": "string"
                  },
                  "list": null,
                  "nullable": true,
                  "choices": null,
                  "defaultValue": {
                    "_special": "SET_TO_NONE"
                  }
                }
              ],
              "join": null
            }
          ],
          "join": null
        },
        {
          "cargs": [
            {
              "tokens": [
                "-input"
              ],
              "join": null
            },
            {
              "tokens": [
                {
                  "base": {
                    "id": 7,
                    "name": "to_nodes",
                    "outputs": [],
                    "docs": {
                      "title": "To nodes",
                      "description": "Specify nodes used for pair calculation when using -from_node.",
                      "authors": [],
                      "literature": [],
                      "urls": []
                    }
                  },
                  "body": {
                    "type": "file",
                    "resolveParent": false,
                    "mutable": false
                  },
                  "list": null,
                  "nullable": true,
                  "choices": null,
                  "defaultValue": {
                    "_special": "SET_TO_NONE"
                  }
                }
              ],
              "join": null
            }
          ],
          "join": null
        }
      ],
      "join": null,
      "docs": {
        "title": null,
        "description": "Calculate shortest distance between node pairs on a surface mesh.",
        "authors": [
          "AFNI Developers"
        ],
        "literature": [],
        "urls": [
          "https://afni.nimh.nih.gov/"
        ]
      }
    },
    "list": null,
    "nullable": false,
    "choices": null,
    "defaultValue": null
  },
  "stdoutAsStringOutput": null,
  "stderrAsStringOutput": null
}