{
  "uid": "d122e00ed8f4305d0e57922fe6e2373707275da9.boutiques",
  "command": {
    "base": {
      "id": 4,
      "name": "t4img_4dfp",
      "outputs": [
        {
          "id": 3,
          "name": "transformed_image",
          "tokens": [
            {
              "refId": 2,
              "fileRemoveSuffixes": [],
              "fallback": null
            },
            ".4dfp.img"
          ],
          "docs": {
            "title": "Transformed Image",
            "description": "The transformed output image file in 4dfp format.",
            "authors": [],
            "literature": [],
            "urls": []
          },
          "mediaTypes": []
        }
      ],
      "docs": {
        "title": "t4img_4dfp",
        "description": "Transforms a 4dfp image using a specified t4 file.",
        "authors": [
          "FreeSurfer Developers"
        ],
        "literature": [],
        "urls": [
          "https://github.com/freesurfer/freesurfer"
        ]
      }
    },
    "body": {
      "type": "struct",
      "name": "t4img_4dfp",
      "publicName": null,
      "groups": [
        {
          "cargs": [
            {
              "tokens": [
                "t4img_4dfp"
              ],
              "join": null
            }
          ],
          "join": null
        },
        {
          "cargs": [
            {
              "tokens": [
                {
                  "base": {
                    "id": 0,
                    "name": "t4file",
                    "outputs": [],
                    "docs": {
                      "title": "T4 File",
                      "description": "Transformation matrix file (t4 file format).",
                      "authors": [],
                      "literature": [],
                      "urls": []
                    }
                  },
                  "body": {
                    "type": "file",
                    "resolveParent": false,
                    "mutable": false,
                    "mediaTypes": []
                  },
                  "list": null,
                  "nullable": false,
                  "choices": null,
                  "defaultValue": null
                }
              ],
              "join": null
            }
          ],
          "join": null
        },
        {
          "cargs": [
            {
              "tokens": [
                {
                  "base": {
                    "id": 1,
                    "name": "imgfile",
                    "outputs": [],
                    "docs": {
                      "title": "Input Image File",
                      "description": "Input image file (4dfp format).",
                      "authors": [],
                      "literature": [],
                      "urls": []
                    }
                  },
                  "body": {
                    "type": "file",
                    "resolveParent": false,
                    "mutable": false,
                    "mediaTypes": []
                  },
                  "list": null,
                  "nullable": false,
                  "choices": null,
                  "defaultValue": null
                }
              ],
              "join": null
            }
          ],
          "join": null
        },
        {
          "cargs": [
            {
              "tokens": [
                {
                  "base": {
                    "id": 2,
                    "name": "outfile",
                    "outputs": [],
                    "docs": {
                      "title": "Output Image File",
                      "description": "Output image file (optional, defaults to <imgfile>t if not provided).",
                      "authors": [],
                      "literature": [],
                      "urls": []
                    }
                  },
                  "body": {
                    "type": "string"
                  },
                  "list": null,
                  "nullable": true,
                  "choices": null,
                  "defaultValue": {
                    "_special": "SET_TO_NONE"
                  }
                }
              ],
              "join": null
            }
          ],
          "join": null
        }
      ],
      "join": null,
      "docs": {
        "title": "t4img_4dfp",
        "description": "Transforms a 4dfp image using a specified t4 file.",
        "authors": [
          "FreeSurfer Developers"
        ],
        "literature": [],
        "urls": [
          "https://github.com/freesurfer/freesurfer"
        ]
      }
    },
    "list": null,
    "nullable": false,
    "choices": null,
    "defaultValue": null
  },
  "captureStdout": null,
  "captureStderr": null,
  "project": {
    "name": "unknown",
    "version": "0.1.0",
    "docs": {
      "title": null,
      "description": null,
      "authors": [],
      "literature": [],
      "urls": []
    },
    "license": null,
    "extras": {}
  },
  "_sSetUp": false
}